pr2apisdk/__init__.py
pr2apisdk-1.0.0.dist-info/LICENSE
pr2apisdk-1.0.0.dist-info/METADATA
pr2apisdk-1.0.0.dist-info/WHEEL
pr2apisdk-1.0.0.dist-info/top_level.txt
pr2apisdk-1.0.0.dist-info/RECORD
