Metadata-Version: 2.1
Name: pr2apisdk
Version: 1.0.0
Summary: Api Sdk For Python
Home-page: https://github.com/pr2apisdk/pr2apisdk_python
Author: pr2apisdk
Author-email: pr2apisdk@outlook.com
License: UNKNOWN
Platform: UNKNOWN
Classifier: Programming Language :: Python :: 3
Classifier: License :: OSI Approved :: MIT License
Requires-Python: >=3.5
License-File: LICENSE
